LICENSE
MANIFEST.in
README.md
requirements.txt
setup.py
moac_tester/__init__.py
moac_tester/constants.py
moac_tester/exceptions.py
moac_tester/main.py
moac_tester/rpc.py
moac_tester.egg-info/PKG-INFO
moac_tester.egg-info/SOURCES.txt
moac_tester.egg-info/dependency_links.txt
moac_tester.egg-info/not-zip-safe
moac_tester.egg-info/requires.txt
moac_tester.egg-info/top_level.txt
moac_tester/backends/__init__.py
moac_tester/backends/base.py
moac_tester/backends/common.py
moac_tester/backends/mock/__init__.py
moac_tester/backends/mock/factory.py
moac_tester/backends/mock/main.py
moac_tester/backends/mock/serializers.py
moac_tester/normalization/__init__.py
moac_tester/normalization/base.py
moac_tester/normalization/common.py
moac_tester/normalization/default.py
moac_tester/normalization/inbound.py
moac_tester/normalization/outbound.py
moac_tester/utils/__init__.py
moac_tester/utils/accounts.py
moac_tester/utils/address.py
moac_tester/utils/backend_testing.py
moac_tester/utils/emitter_contract.py
moac_tester/utils/encoding.py
moac_tester/utils/filters.py
moac_tester/utils/formatting.py
moac_tester/utils/jacobian.py
moac_tester/utils/math_contract.py
moac_tester/utils/module_loading.py
moac_tester/utils/secp256k1.py
moac_tester/utils/throws_contract.py
moac_tester/utils/transactions.py
moac_tester/validation/__init__.py
moac_tester/validation/base.py
moac_tester/validation/common.py
moac_tester/validation/default.py
moac_tester/validation/inbound.py
moac_tester/validation/outbound.py