Metadata-Version: 1.1
Name: moac-tester
Version: 0.1.3
Summary: Tools for testing Moac applications.
Home-page: https://github.com/wanpixiaozi/moac-tester
Author: Zhenglong Cai
Author-email: caizl2002@hotmail.com
License: MIT
Keywords: moac
Platform: UNKNOWN
Classifier: Development Status :: 2 - Pre-Alpha
Classifier: Intended Audience :: Developers
Classifier: License :: OSI Approved :: MIT License
Classifier: Natural Language :: English
Classifier: Programming Language :: Python :: 3
Classifier: Programming Language :: Python :: 3.5
Classifier: Programming Language :: Python :: 3.6
Classifier: Programming Language :: Python :: 3.7
